pianogen/__init__.py
pianogen/commonTracks.py
pianogen/parse_to_npy.py
pianogen-0.0.6.data/data/LICENSE.txt
pianogen-0.0.6.dist-info/LICENSE.txt
pianogen-0.0.6.dist-info/METADATA
pianogen-0.0.6.dist-info/WHEEL
pianogen-0.0.6.dist-info/top_level.txt
pianogen-0.0.6.dist-info/RECORD
