Metadata-Version: 2.1
Name: pianogen
Version: 0.0.6
Summary: Pianoroll-generator A package to generate pianoroll (NPZ) datasets
Home-page: https://github.com/cliffordkleinsr/pianoroll-generator
Author: Clifford Njoroge
Author-email: cnjoroge@gmail.com
Classifier: Programming Language :: Python :: 3
Classifier: Programming Language :: Python :: 3.7
Classifier: Programming Language :: Python :: 3.8
Classifier: Programming Language :: Python :: 3.9
Classifier: Programming Language :: Python :: 3.10
Classifier: License :: OSI Approved :: MIT License
Classifier: Operating System :: OS Independent
Requires-Python: >=3.10
License-File: LICENSE.txt
Requires-Dist: pypianoroll ==0.5.3
Requires-Dist: numpy
